nabPy/__init__.py
nabPy/__init__.py:Zone.Identifier
nabPy/basicFunctions.py
nabPy/basicFunctions.py:Zone.Identifier
nabPy/eventFileClass.py
nabPy/eventFileClass.py:Zone.Identifier
nabPy/fileFormats.py
nabPy/fileFormats.py:Zone.Identifier
nabPy/gpuFunctions.py
nabPy/gpuFunctions.py:Zone.Identifier
nabPy/nabPy.py
nabPy/nabPy.py:Zone.Identifier
nabPy/parameterFileClass.py
nabPy/parameterFileClass.py:Zone.Identifier
nabPy/replay.py
nabPy/replay.py:Zone.Identifier
nabPy/resultFileClass.py
nabPy/resultFileClass.py:Zone.Identifier
nabPy/temperatureFileClass.py
nabPy/temperatureFileClass.py:Zone.Identifier
nabPy/triggerFileClass.py
nabPy/triggerFileClass.py:Zone.Identifier
nabPy/waveformFileClass.py
nabPy/waveformFileClass.py:Zone.Identifier
nabPy-0.1.65.dist-info/METADATA
nabPy-0.1.65.dist-info/PKG-INFO:Zone.Identifier
nabPy-0.1.65.dist-info/SOURCES.txt:Zone.Identifier
nabPy-0.1.65.dist-info/WHEEL
nabPy-0.1.65.dist-info/dependency_links.txt:Zone.Identifier
nabPy-0.1.65.dist-info/requires.txt:Zone.Identifier
nabPy-0.1.65.dist-info/top_level.txt
nabPy-0.1.65.dist-info/top_level.txt:Zone.Identifier
nabPy-0.1.65.dist-info/RECORD
