Metadata-Version: 2.1
Name: nabPy
Version: 0.1.65
Summary: Python Library for the Nab Experiment
Home-page: https://gitlab.com/NabExperiment/pyNab/
Author: David Mathews
Author-email: david.mathews.1994@gmail.com
License: MIT
Requires-Python: >=3.6
Requires-Dist: dask
Requires-Dist: h5py
Requires-Dist: matplotlib
Requires-Dist: numba
Requires-Dist: numpy
Requires-Dist: pillow
Requires-Dist: scipy
Requires-Dist: pandas
Requires-Dist: bokeh
Requires-Dist: tqdm
